meld_mcp/__init__.py
meld_mcp/__main__.py
meld_mcp/api_client.py
meld_mcp/config.py
meld_mcp/hooks.py
meld_mcp/server.py
meld_mcp-0.1.7.dist-info/METADATA
meld_mcp-0.1.7.dist-info/WHEEL
meld_mcp-0.1.7.dist-info/entry_points.txt
meld_mcp-0.1.7.dist-info/RECORD
