Metadata-Version: 2.4
Name: meld-mcp
Version: 0.1.7
Summary: Meld MCP Server - Connects Claude Code to Meld cloud
Project-URL: Homepage, https://meld.run
Project-URL: Documentation, https://meld.run
Author: Phil Glazer
License-Expression: MIT
Classifier: Development Status :: 3 - Alpha
Classifier: Intended Audience :: Developers
Classifier: License :: OSI Approved :: MIT License
Classifier: Programming Language :: Python :: 3.11
Classifier: Programming Language :: Python :: 3.12
Requires-Python: >=3.11
Requires-Dist: httpx>=0.27.0
Requires-Dist: mcp>=1.0.0
Requires-Dist: pydantic>=2.0.0
Provides-Extra: dev
Requires-Dist: pytest>=8.0.0; extra == 'dev'
Requires-Dist: ruff>=0.5.0; extra == 'dev'
